raven_aiohttp.py
raven_aiohttp-0.7.0.dist-info/DESCRIPTION.rst
raven_aiohttp-0.7.0.dist-info/METADATA
raven_aiohttp-0.7.0.dist-info/RECORD
raven_aiohttp-0.7.0.dist-info/WHEEL
raven_aiohttp-0.7.0.dist-info/metadata.json
raven_aiohttp-0.7.0.dist-info/top_level.txt
