Metadata-Version: 2.0
Name: raven-aiohttp
Version: 0.7.0
Summary: An asyncio transport for raven-python
Home-page: https://github.com/getsentry/raven-aiohttp
Author: David Cramer
Author-email: dcramer@gmail.com
License: BSD
Platform: UNKNOWN
Classifier: Intended Audience :: Developers
Classifier: Intended Audience :: System Administrators
Classifier: Operating System :: OS Independent
Classifier: Programming Language :: Python
Classifier: Programming Language :: Python :: 3
Classifier: Programming Language :: Python :: 3.4
Classifier: Programming Language :: Python :: 3.5
Classifier: Programming Language :: Python :: 3.6
Classifier: Programming Language :: Python :: 3 :: Only
Classifier: Topic :: Software Development
Provides-Extra: test
Requires-Dist: aiohttp (>=2.0)
Requires-Dist: raven (>=5.4.0)
Provides-Extra: test
Requires-Dist: flake8; extra == 'test'
Requires-Dist: isort; extra == 'test'
Requires-Dist: pytest; extra == 'test'
Requires-Dist: pytest-asyncio (<0.6.0); extra == 'test'
Requires-Dist: pytest-cov; extra == 'test'
Requires-Dist: pytest-mock; extra == 'test'
